TengxunDaimaAnquanZhinanFix1/README.md
TengxunDaimaAnquanZhinanFix1/__init__.py
TengxunDaimaAnquanZhinanFix1/__main__.py
TengxunDaimaAnquanZhinanFix1/file.epub
TengxunDaimaAnquanZhinanFix1/index.html
TengxunDaimaAnquanZhinanFix1/css/__init__.py
TengxunDaimaAnquanZhinanFix1/css/annotations.css
TengxunDaimaAnquanZhinanFix1/css/main.css
TengxunDaimaAnquanZhinanFix1/css/normalize.css
TengxunDaimaAnquanZhinanFix1/css/popup.css
TengxunDaimaAnquanZhinanFix1/font/__init__.py
TengxunDaimaAnquanZhinanFix1/font/fontello.eot
TengxunDaimaAnquanZhinanFix1/font/fontello.svg
TengxunDaimaAnquanZhinanFix1/font/fontello.ttf
TengxunDaimaAnquanZhinanFix1/font/fontello.woff
TengxunDaimaAnquanZhinanFix1/img/__init__.py
TengxunDaimaAnquanZhinanFix1/img/annotator-glyph-sprite.png
TengxunDaimaAnquanZhinanFix1/img/annotator-icon-sprite.png
TengxunDaimaAnquanZhinanFix1/img/apple-touch-icon.png
TengxunDaimaAnquanZhinanFix1/img/cancelfullscreen.png
TengxunDaimaAnquanZhinanFix1/img/close.png
TengxunDaimaAnquanZhinanFix1/img/fullscreen.png
TengxunDaimaAnquanZhinanFix1/img/loader.gif
TengxunDaimaAnquanZhinanFix1/img/menu-icon.png
TengxunDaimaAnquanZhinanFix1/img/save.png
TengxunDaimaAnquanZhinanFix1/img/saved.png
TengxunDaimaAnquanZhinanFix1/img/settings-s.png
TengxunDaimaAnquanZhinanFix1/img/settings.png
TengxunDaimaAnquanZhinanFix1/img/star.png
TengxunDaimaAnquanZhinanFix1/js/__init__.py
TengxunDaimaAnquanZhinanFix1/js/epub.js
TengxunDaimaAnquanZhinanFix1/js/epub.min.js
TengxunDaimaAnquanZhinanFix1/js/epub.min.map
TengxunDaimaAnquanZhinanFix1/js/hooks.min.js
TengxunDaimaAnquanZhinanFix1/js/hooks.min.map
TengxunDaimaAnquanZhinanFix1/js/reader.js
TengxunDaimaAnquanZhinanFix1/js/reader.js.map
TengxunDaimaAnquanZhinanFix1/js/reader.min.js
TengxunDaimaAnquanZhinanFix1/js/reader.min.map
TengxunDaimaAnquanZhinanFix1/js/hooks/__init__.py
TengxunDaimaAnquanZhinanFix1/js/hooks/extensions/__init__.py
TengxunDaimaAnquanZhinanFix1/js/hooks/extensions/highlight.js
tengxun_daima_anquan_zhinan_fix1-2025.3.25.0.dist-info/METADATA
tengxun_daima_anquan_zhinan_fix1-2025.3.25.0.dist-info/WHEEL
tengxun_daima_anquan_zhinan_fix1-2025.3.25.0.dist-info/entry_points.txt
tengxun_daima_anquan_zhinan_fix1-2025.3.25.0.dist-info/top_level.txt
tengxun_daima_anquan_zhinan_fix1-2025.3.25.0.dist-info/RECORD
